deep/__init__.py
deep/thread_local.py
deep/utils.py
deep/version.py
deep/api/__init__.py
deep/api/deep.py
deep/api/types.py
deep/api/attributes/__init__.py
deep/api/auth/__init__.py
deep/api/plugin/__init__.py
deep/api/plugin/otel.py
deep/api/plugin/python.py
deep/api/plugin/metric/__init__.py
deep/api/plugin/metric/otel_metrics.py
deep/api/plugin/metric/prometheus_metrics.py
deep/api/plugin/span/__init__.py
deep/api/resource/__init__.py
deep/api/tracepoint/__init__.py
deep/api/tracepoint/constants.py
deep/api/tracepoint/eventsnapshot.py
deep/api/tracepoint/tracepoint_config.py
deep/api/tracepoint/trigger.py
deep/config/__init__.py
deep/config/config_service.py
deep/config/tracepoint_config.py
deep/grpc/__init__.py
deep/grpc/grpc_service.py
deep/logging/__init__.py
deep/logging/logging.conf
deep/poll/__init__.py
deep/poll/poll.py
deep/processor/__init__.py
deep/processor/frame_collector.py
deep/processor/frame_config.py
deep/processor/trigger_handler.py
deep/processor/variable_processor.py
deep/processor/variable_set_processor.py
deep/processor/bfs/__init__.py
deep/processor/context/__init__.py
deep/processor/context/action_context.py
deep/processor/context/action_results.py
deep/processor/context/callback_context.py
deep/processor/context/log_action.py
deep/processor/context/metric_action.py
deep/processor/context/snapshot_action.py
deep/processor/context/span_action.py
deep/processor/context/trigger_context.py
deep/push/__init__.py
deep/push/push_service.py
deep/task/__init__.py
deep_agent-1.1.2.dist-info/METADATA
deep_agent-1.1.2.dist-info/WHEEL
deep_agent-1.1.2.dist-info/licenses/LICENSE
deep_agent-1.1.2.dist-info/RECORD
