Metadata-Version: 2.3
Name: deep-agent
Version: 1.1.2
Summary: DEEP Python Agent
Author-email: Intergral GmbH <support@intergral.com>, Ben Donnelly <b.w.donnelly1@gmail.com>
License: AGPL-3.0-only
Classifier: Development Status :: 5 - Production/Stable
Classifier: Intended Audience :: Developers
Classifier: License :: OSI Approved :: GNU Affero General Public License v3
Classifier: Programming Language :: Python
Classifier: Programming Language :: Python :: 3
Classifier: Programming Language :: Python :: 3.7
Classifier: Programming Language :: Python :: 3.8
Classifier: Programming Language :: Python :: 3.9
Classifier: Programming Language :: Python :: 3.10
Classifier: Programming Language :: Python :: 3.11
Classifier: Programming Language :: Python :: 3.12
Classifier: Typing :: Typed
Requires-Python: >3.7
Requires-Dist: deep-proto>=1.0.5
Requires-Dist: grpcio>=1.51.3
Requires-Dist: protobuf>=3.20.3
